res_reg_lmnt_awikner/ResData.py
res_reg_lmnt_awikner/RunOpts.py
res_reg_lmnt_awikner/__init__.py
res_reg_lmnt_awikner/csc_mult.py
res_reg_lmnt_awikner/get_windows_path.py
res_reg_lmnt_awikner/ks_etdrk4.py
res_reg_lmnt_awikner/lorenzrungekutta_numba.py
res_reg_lmnt_awikner/poincare_max.py
res_reg_lmnt_awikner/poincare_max_peaks.py
res_reg_lmnt_awikner/process_test_data.py
res_reg_lmnt_awikner/reservoir_train_test.py
res_reg_lmnt_awikner/set_numba.py
res_reg_lmnt_awikner/slurm-launch.py
res_reg_lmnt_awikner/slurm-template.sh
res_reg_lmnt_awikner/start_deepthought2_run.py
res_reg_lmnt_awikner-0.0.1.dist-info/METADATA
res_reg_lmnt_awikner-0.0.1.dist-info/WHEEL
res_reg_lmnt_awikner-0.0.1.dist-info/licenses/LICENSE
res_reg_lmnt_awikner-0.0.1.dist-info/RECORD
