Metadata-Version: 2.1
Name: res_reg_lmnt_awikner
Version: 0.0.1
Summary: Package for testing regularization performance on reservoir computer predictions
Project-URL: Homepage, https://github.com/awikner/res-noise-stabilization
Author-email: Alexander Wikner <apwikner@gmail.com>
License: MIT License
Classifier: License :: OSI Approved :: MIT License
Classifier: Operating System :: OS Independent
Classifier: Programming Language :: Python :: 3
Requires-Python: >=3.9
Requires-Dist: matplotlib==3.5.2
Requires-Dist: numba==0.55.2
Requires-Dist: numpy==1.22.4
Requires-Dist: pandas==1.4.3
Requires-Dist: ray==1.13.0
Requires-Dist: scipy==1.8.1
Requires-Dist: tqdm==4.64.0
